collision/collision.abi3.so
racingenv/Resources/Textures/Car.png
racingenv/Resources/Textures/Track.png
racingenv/Resources/Tracks/Hockenheim.xml
racingenv/__init__.py
racingenv/editors/__init__.py
racingenv/editors/physicseditor.py
racingenv/env/__init__.py
racingenv/env/racing.py
racingenv/physics/__init__.py
racingenv/physics/car.py
racingenv/physics/nativecollisionhandler.py
racingenv/physics/simulation.py
racingenv/physics/track.py
racingenv/physics/utils.py
racingenv/renderer/__init__.py
racingenv/renderer/camera.py
racingenv/renderer/carrenderer.py
racingenv/renderer/resourcemanager.py
racingenv/renderer/simulationrenderer.py
racingenv/renderer/trackrenderer.py
racingenv-2.0.4.dist-info/METADATA
racingenv-2.0.4.dist-info/WHEEL
racingenv-2.0.4.dist-info/entry_points.txt
racingenv-2.0.4.dist-info/licenses/LICENSE
racingenv-2.0.4.dist-info/RECORD
