Metadata-Version: 2.1
Name: racingenv
Version: 2.0.4
Summary: A gymnasium 2D racing environment
Author-Email: Laurenz Levi Spielmann <laurenz-levi.spielmann@tu-dortmund.de>
License: MIT License
Requires-Python: >=3.8
License-File: LICENSE
